ci_ynh/__init__.py
ci_ynh/admin.py
ci_ynh/huey_instance.py
ci_ynh/management/commands/ci_run.py
ci_ynh/migrations/0001_initial.py
ci_ynh/migrations/0002_auto_20210108_1104.py
ci_ynh/migrations/__init__.py
ci_ynh/models.py
ci_ynh/tasks.py
ci_ynh/yunohost_utils.py
ci_ynh-0.1.0a1.dist-info/LICENSE
ci_ynh-0.1.0a1.dist-info/WHEEL
ci_ynh-0.1.0a1.dist-info/METADATA
ci_ynh-0.1.0a1.dist-info/RECORD
