Metadata-Version: 2.1
Name: ci-ynh
Version: 0.1.0a1
Summary: CI for YunoHost to test YunoHost packages ;)
Home-page: https://github.com/YunoHost-Apps/ci_ynh
License: GPL
Author: JensDiemer
Author-email: git@jensdiemer.de
Requires-Python: >=3.7,<4.0.0
Classifier: License :: Other/Proprietary License
Classifier: Programming Language :: Python :: 3
Classifier: Programming Language :: Python :: 3.7
Classifier: Programming Language :: Python :: 3.8
Classifier: Programming Language :: Python :: 3.9
Requires-Dist: bx_py_utils
Requires-Dist: django
Requires-Dist: django-axes
Requires-Dist: django-huey-monitor
Requires-Dist: django-redis
Requires-Dist: django_ynh
Requires-Dist: gunicorn
Requires-Dist: huey
Requires-Dist: psycopg2-binary
